sigla/__init__.py
sigla/cli/__init__.py
sigla/cli/actions.py
sigla/cli/cli.py
sigla/cli/commands.py
sigla/config.py
sigla/data/__init__.py
sigla/data/data.py
sigla/data/loaders.py
sigla/frontmatter/__init__.py
sigla/frontmatter/frontmatter.py
sigla/main.py
sigla/node_factory.py
sigla/node_loaders.py
sigla/nodes/__init__.py
sigla/nodes/abstract_node.py
sigla/nodes/node.py
sigla/nodes/node_echo.py
sigla/nodes/node_file.py
sigla/nodes/node_list.py
sigla/nodes/node_template.py
sigla/templates/__init__.py
sigla/templates/engines.py
sigla/templates/loaders.py
sigla/utils/__init__.py
sigla/utils/errors.py
sigla/utils/filters.py
sigla/utils/helpers.py
sigla/utils/type_casters.py
sigla-0.0.64.dist-info/entry_points.txt
sigla-0.0.64.dist-info/LICENSE
sigla-0.0.64.dist-info/WHEEL
sigla-0.0.64.dist-info/METADATA
sigla-0.0.64.dist-info/RECORD
